contextualSpellCheck/__init__.py
contextualSpellCheck/contextualSpellCheck.py
contextualSpellCheck/data/vocab.txt
contextualSpellCheck/tests/__init__.py
contextualSpellCheck/tests/test_contextualSpellCheck.py
contextualSpellCheck-0.4.4.dist-info/LICENSE
contextualSpellCheck-0.4.4.dist-info/METADATA
contextualSpellCheck-0.4.4.dist-info/WHEEL
contextualSpellCheck-0.4.4.dist-info/top_level.txt
contextualSpellCheck-0.4.4.dist-info/RECORD
