Metadata-Version: 2.1
Name: contextualSpellCheck
Version: 0.4.4
Summary: Contextual spell correction using BERT (bidirectional representations)
Home-page: https://github.com/R1j1t/contextualSpellCheck
Author: R1j1t
Author-email: r1j1t@protonmail.com
Classifier: Programming Language :: Python :: 3
Classifier: Programming Language :: Python :: 3.6
Classifier: Programming Language :: Python :: 3.7
Classifier: Programming Language :: Python :: 3.8
Classifier: Programming Language :: Python :: 3.9
Classifier: License :: OSI Approved :: MIT License
Classifier: Operating System :: OS Independent
Classifier: Topic :: Scientific/Engineering :: Artificial Intelligence
Classifier: Intended Audience :: Developers
Classifier: Intended Audience :: Education
Classifier: Intended Audience :: Science/Research
Classifier: Development Status :: 4 - Beta
Requires-Python: >=3.6
License-File: LICENSE
Requires-Dist: torch >=1.4
Requires-Dist: editdistance ==0.6.2
Requires-Dist: transformers >=4.0.0
Requires-Dist: spacy >=3.0.0
